tim_asinc_chat/__init__.py
tim_asinc_chat/ChatWindow/__init__.py
tim_asinc_chat/ChatWindow/first_form.ui
tim_asinc_chat/ChatWindow/form.ui
tim_asinc_chat/ChatWindow/ui_first_form.py
tim_asinc_chat/ChatWindow/ui_form.py
tim_asinc_chat/client_gui.py
tim_asinc_chat/first_form.py
tim_asinc_chat/gui.py
tim_asinc_chat/metaclass.py
tim_asinc_chat/models.py
tim_asinc_chat/output/tim_asicn_chat_client/__init__.py
tim_asinc_chat/output/tim_asicn_chat_client/base_library.zip
tim_asinc_chat/output/tim_asicn_chat_client/ChatWindow/__init__.py
tim_asinc_chat/output/tim_asicn_chat_client/ChatWindow/first_form.ui
tim_asinc_chat/output/tim_asicn_chat_client/ChatWindow/form.ui
tim_asinc_chat/output/tim_asicn_chat_client/ChatWindow/ui_first_form.py
tim_asinc_chat/output/tim_asicn_chat_client/ChatWindow/ui_form.py
tim_asinc_chat/output/tim_asicn_chat_client/client_gui.py
tim_asinc_chat/output/tim_asicn_chat_client/first_form.py
tim_asinc_chat/output/tim_asicn_chat_client/gui.py
tim_asinc_chat/output/tim_asicn_chat_client/libcrypto-1_1.dll
tim_asinc_chat/output/tim_asicn_chat_client/libffi-7.dll
tim_asinc_chat/output/tim_asicn_chat_client/libssl-1_1.dll
tim_asinc_chat/output/tim_asicn_chat_client/metaclass.py
tim_asinc_chat/output/tim_asicn_chat_client/models.py
tim_asinc_chat/output/tim_asicn_chat_client/PySide6/MSVCP140.dll
tim_asinc_chat/output/tim_asicn_chat_client/PySide6/MSVCP140_1.dll
tim_asinc_chat/output/tim_asicn_chat_client/PySide6/MSVCP140_2.dll
tim_asinc_chat/output/tim_asicn_chat_client/PySide6/opengl32sw.dll
tim_asinc_chat/output/tim_asicn_chat_client/PySide6/plugins/generic/qtuiotouchplugin.dll
tim_asinc_chat/output/tim_asicn_chat_client/PySide6/plugins/iconengines/qsvgicon.dll
tim_asinc_chat/output/tim_asicn_chat_client/PySide6/plugins/imageformats/qgif.dll
tim_asinc_chat/output/tim_asicn_chat_client/PySide6/plugins/imageformats/qicns.dll
tim_asinc_chat/output/tim_asicn_chat_client/PySide6/plugins/imageformats/qico.dll
tim_asinc_chat-0.1.0.dist-info/LICENSE
tim_asinc_chat-0.1.0.dist-info/METADATA
tim_asinc_chat-0.1.0.dist-info/WHEEL
tim_asinc_chat-0.1.0.dist-info/RECORD
