Metadata-Version: 2.1
Name: tim-asinc-chat
Version: 0.1.0
Summary: 
Author: T1monation
Author-email: 4timonaton@gmail.com
Requires-Python: >=3.10,<3.11
Classifier: Programming Language :: Python :: 3
Classifier: Programming Language :: Python :: 3.10
Requires-Dist: alembic (>=1.11.1,<2.0.0)
Requires-Dist: chardet (>=5.1.0,<6.0.0)
Requires-Dist: postgres (>=4.0,<5.0)
Requires-Dist: pyqt6 (>=6.5.1,<7.0.0)
Requires-Dist: pyside6 (>=6.5.1.1,<7.0.0.0)
Requires-Dist: pyyaml (>=6.0,<7.0)
Requires-Dist: sqlalchemy (>=2.0.15,<3.0.0)
Requires-Dist: tabulate (>=0.9.0,<0.10.0)
